a_pandas_ex_easy_loc/README.md
a_pandas_ex_easy_loc/__init__.py
a_pandas_ex_easy_loc/requirements.txt
a_pandas_ex_easy_loc/thirdparty.json
a_pandas_ex_easy_loc-0.15.dist-info/LICENSE.rst
a_pandas_ex_easy_loc-0.15.dist-info/METADATA
a_pandas_ex_easy_loc-0.15.dist-info/WHEEL
a_pandas_ex_easy_loc-0.15.dist-info/top_level.txt
a_pandas_ex_easy_loc-0.15.dist-info/RECORD
