Metadata-Version: 2.1
Name: a-pandas-ex-easy-loc
Version: 0.15
Summary: Search and replace values with df.loc without Exceptions due to dtype incompatibility
Home-page: https://github.com/hansalemaos/a_pandas_ex_easy_loc
Author: Johannes Fischer
Author-email: aulasparticularesdealemaosp@gmail.com
License: MIT
Keywords: loc,iloc,df.at,df.iat,pandas,DataFrame,Series
Classifier: Development Status :: 4 - Beta
Classifier: Programming Language :: Python :: 3 :: Only
Classifier: Programming Language :: Python :: 3.10
Classifier: Topic :: Software Development :: Libraries :: Python Modules
Classifier: Topic :: Utilities
License-File: LICENSE.rst
Requires-Dist: a-pandas-ex-less-memory-more-speed
Requires-Dist: a-pandas-ex-plode-tool
Requires-Dist: cprinter
Requires-Dist: flatten-everything
Requires-Dist: numpy
Requires-Dist: pandas
